{
  "updated": "2026-06-12T17:10:18.615Z",
  "trends": [
    {
      "googleTrend": "spacex stock",
      "searchVolume": "5,000+",
      "started": "3 小時前"
    },
    {
      "googleTrend": "平野 惠 一",
      "searchVolume": "2,000+",
      "started": "2 小時前"
    },
    {
      "googleTrend": "岡山本洲工業區",
      "searchVolume": "2,000+",
      "started": "3 小時前"
    },
    {
      "googleTrend": "spxc",
      "searchVolume": "1,000+",
      "started": "3 小時前"
    },
    {
      "googleTrend": "侯 昌明",
      "searchVolume": "200+",
      "started": "20 分鐘前"
    },
    {
      "googleTrend": "rklb",
      "searchVolume": "100+",
      "started": "50 分鐘前"
    },
    {
      "googleTrend": "金南佶",
      "searchVolume": "500+",
      "started": "1 小時前"
    },
    {
      "googleTrend": "巴拉圭",
      "searchVolume": "100+",
      "started": "20 分鐘前"
    },
    {
      "googleTrend": "plg",
      "searchVolume": "500+",
      "started": "3 小時前"
    },
    {
      "googleTrend": "回測",
      "searchVolume": "100+",
      "started": "30 分鐘前"
    },
    {
      "googleTrend": "台 玻",
      "searchVolume": "200+",
      "started": "3 小時前"
    },
    {
      "googleTrend": "食物",
      "searchVolume": "200+",
      "started": "3 小時前"
    },
    {
      "googleTrend": "meta 股價",
      "searchVolume": "200+",
      "started": "2 小時前"
    },
    {
      "googleTrend": "王柏傑",
      "searchVolume": "200+",
      "started": "2 小時前"
    },
    {
      "googleTrend": "阿松與阿暖",
      "searchVolume": "200+",
      "started": "3 小時前"
    },
    {
      "googleTrend": "spx",
      "searchVolume": "100+",
      "started": "3 小時前"
    },
    {
      "googleTrend": "shakira",
      "searchVolume": "100+",
      "started": "1 小時前"
    }
  ]
}