{
  "updated": "2026-04-27T06:05:24.255Z",
  "trends": [
    {
      "googleTrend": "股東大會",
      "searchVolume": "1,000+",
      "started": "2 小時前"
    },
    {
      "googleTrend": "日圓",
      "searchVolume": "2,000+",
      "started": "1 小時前"
    },
    {
      "googleTrend": "麥當勞 鋼彈",
      "searchVolume": "1,000+",
      "started": "2 小時前"
    },
    {
      "googleTrend": "游盈隆",
      "searchVolume": "500+",
      "started": "2 小時前"
    },
    {
      "googleTrend": "富邦悍將",
      "searchVolume": "1,000+",
      "started": "3 小時前"
    },
    {
      "googleTrend": "公務員",
      "searchVolume": "2,000+",
      "started": "50 分鐘前"
    },
    {
      "googleTrend": "李 多 慧",
      "searchVolume": "500+",
      "started": "3 小時前"
    },
    {
      "googleTrend": "陳力銘",
      "searchVolume": "500+",
      "started": "1 小時前"
    },
    {
      "googleTrend": "台中停電",
      "searchVolume": "500+",
      "started": "40 分鐘前"
    },
    {
      "googleTrend": "台 股",
      "searchVolume": "200+",
      "started": "20 分鐘前"
    },
    {
      "googleTrend": "聯電 股東 會 紀念品",
      "searchVolume": "200+",
      "started": "1 小時前"
    },
    {
      "googleTrend": "湖人",
      "searchVolume": "2,000+",
      "started": "2 小時前"
    },
    {
      "googleTrend": "2408",
      "searchVolume": "500+",
      "started": "10 分鐘前"
    },
    {
      "googleTrend": "行人",
      "searchVolume": "200+",
      "started": "1 小時前"
    },
    {
      "googleTrend": "佳能",
      "searchVolume": "100+",
      "started": "1 小時前"
    },
    {
      "googleTrend": "张凌赫",
      "searchVolume": "100+",
      "started": "1 小時前"
    },
    {
      "googleTrend": "hito 流行音樂獎",
      "searchVolume": "100+",
      "started": "50 分鐘前"
    },
    {
      "googleTrend": "菊元百貨",
      "searchVolume": "100+",
      "started": "40 分鐘前"
    },
    {
      "googleTrend": "湖人對火箭",
      "searchVolume": "200+",
      "started": "1 小時前"
    },
    {
      "googleTrend": "weijia jiang",
      "searchVolume": "200+",
      "started": "1 小時前"
    },
    {
      "googleTrend": "記憶體概念股",
      "searchVolume": "200+",
      "started": "3 小時前"
    },
    {
      "googleTrend": "lakers",
      "searchVolume": "200+",
      "started": "1 小時前"
    },
    {
      "googleTrend": "台達電目標價",
      "searchVolume": "200+",
      "started": "3 小時前"
    },
    {
      "googleTrend": "張雪機車",
      "searchVolume": "100+",
      "started": "1 小時前"
    }
  ]
}