{
  "updated": "2025-08-23T22:37:41.513Z",
  "trends": [
    {
      "googleTrend": "levante vs barcelona",
      "searchVolume": "100+",
      "started": "1 小時前"
    },
    {
      "googleTrend": "萊萬特 對 巴塞隆納",
      "searchVolume": "100+",
      "started": "40 分鐘前"
    },
    {
      "googleTrend": "arsenal đấu với leeds",
      "searchVolume": "100+",
      "started": "1 小時前"
    },
    {
      "googleTrend": "西甲",
      "searchVolume": "200+",
      "started": "2 小時前"
    },
    {
      "googleTrend": "義甲",
      "searchVolume": "100+",
      "started": "3 小時前"
    },
    {
      "googleTrend": "七夕",
      "searchVolume": "200+",
      "started": "3 小時前"
    }
  ]
}