{
  "updated": "2026-05-23T06:26:19.959Z",
  "trends": [
    {
      "googleTrend": "交通部中央气象署",
      "searchVolume": "1,000+",
      "started": "1 小時前"
    },
    {
      "googleTrend": "中國",
      "searchVolume": "1,000+",
      "started": "30 分鐘前"
    },
    {
      "googleTrend": "3 小時前",
      "searchVolume": "2,000+",
      "started": "3 小時前"
    },
    {
      "googleTrend": "陳玉珍",
      "searchVolume": "500+",
      "started": "2 小時前"
    },
    {
      "googleTrend": "上海",
      "searchVolume": "500+",
      "started": "2 小時前"
    },
    {
      "googleTrend": "執政黨",
      "searchVolume": "500+",
      "started": "3 小時前"
    },
    {
      "googleTrend": "光宝科技",
      "searchVolume": "500+",
      "started": "3 小時前"
    },
    {
      "googleTrend": "南亞 科技",
      "searchVolume": "1,000+",
      "started": "3 小時前"
    },
    {
      "googleTrend": "黃暐瀚",
      "searchVolume": "500+",
      "started": "3 小時前"
    },
    {
      "googleTrend": "白宮",
      "searchVolume": "500+",
      "started": "2 小時前"
    },
    {
      "googleTrend": "麗嬰房",
      "searchVolume": "500+",
      "started": "2 小時前"
    },
    {
      "googleTrend": "呂坤修",
      "searchVolume": "200+",
      "started": "2 小時前"
    },
    {
      "googleTrend": "chiikawa days 台北特展",
      "searchVolume": "1,000+",
      "started": "2 小時前"
    },
    {
      "googleTrend": "勇者鬥惡龍",
      "searchVolume": "200+",
      "started": "2 小時前"
    },
    {
      "googleTrend": "6531",
      "searchVolume": "200+",
      "started": "1 小時前"
    },
    {
      "googleTrend": "沈慶京",
      "searchVolume": "200+",
      "started": "1 小時前"
    },
    {
      "googleTrend": "山邊媽祖",
      "searchVolume": "200+",
      "started": "3 小時前"
    },
    {
      "googleTrend": "馬刺 雷霆",
      "searchVolume": "1,000+",
      "started": "3 小時前"
    },
    {
      "googleTrend": "宏碁",
      "searchVolume": "100+",
      "started": "30 分鐘前"
    },
    {
      "googleTrend": "五月天演唱會門票",
      "searchVolume": "1,000+",
      "started": "3 小時前"
    },
    {
      "googleTrend": "少子化",
      "searchVolume": "100+",
      "started": "30 分鐘前"
    },
    {
      "googleTrend": "台北國際旅展",
      "searchVolume": "200+",
      "started": "3 小時前"
    },
    {
      "googleTrend": "jared mccain",
      "searchVolume": "200+",
      "started": "2 小時前"
    },
    {
      "googleTrend": "中正紀念堂",
      "searchVolume": "100+",
      "started": "20 分鐘前"
    },
    {
      "googleTrend": "拿坡里",
      "searchVolume": "500+",
      "started": "3 小時前"
    }
  ]
}