{
  "updated": "2026-05-19T01:13:10.580Z",
  "trends": [
    {
      "googleTrend": "雷霆 對 馬刺",
      "searchVolume": "5,000+",
      "started": "1 小時前"
    },
    {
      "googleTrend": "spurs vs thunder",
      "searchVolume": "500+",
      "started": "30 分鐘前"
    },
    {
      "googleTrend": "nba線上看",
      "searchVolume": "1,000+",
      "started": "10 分鐘前"
    },
    {
      "googleTrend": "漢他病毒",
      "searchVolume": "500+",
      "started": "2 小時前"
    },
    {
      "googleTrend": "大立光",
      "searchVolume": "200+",
      "started": "1 小時前"
    },
    {
      "googleTrend": "沙丁魚",
      "searchVolume": "200+",
      "started": "2 小時前"
    },
    {
      "googleTrend": "playstation",
      "searchVolume": "200+",
      "started": "1 小時前"
    },
    {
      "googleTrend": "顏志琳",
      "searchVolume": "100+",
      "started": "1 小時前"
    },
    {
      "googleTrend": "國民年金",
      "searchVolume": "1,000+",
      "started": "3 小時前"
    },
    {
      "googleTrend": "事欣科",
      "searchVolume": "100+",
      "started": "10 分鐘前"
    },
    {
      "googleTrend": "鎧俠股價",
      "searchVolume": "100+",
      "started": "30 分鐘前"
    },
    {
      "googleTrend": "費城半導體指數",
      "searchVolume": "1,000+",
      "started": "3 小時前"
    },
    {
      "googleTrend": "wha",
      "searchVolume": "100+",
      "started": "2 小時前"
    },
    {
      "googleTrend": "郭忠祐",
      "searchVolume": "200+",
      "started": "2 小時前"
    },
    {
      "googleTrend": "低軌衛星",
      "searchVolume": "100+",
      "started": "10 分鐘前"
    },
    {
      "googleTrend": "群創光電",
      "searchVolume": "500+",
      "started": "3 小時前"
    },
    {
      "googleTrend": "21 世紀 大 君 夫人",
      "searchVolume": "200+",
      "started": "2 小時前"
    },
    {
      "googleTrend": "虞書欣",
      "searchVolume": "200+",
      "started": "2 小時前"
    },
    {
      "googleTrend": "鈾",
      "searchVolume": "200+",
      "started": "2 小時前"
    },
    {
      "googleTrend": "辜仲諒",
      "searchVolume": "100+",
      "started": "1 小時前"
    },
    {
      "googleTrend": "端午节",
      "searchVolume": "200+",
      "started": "3 小時前"
    },
    {
      "googleTrend": "股份",
      "searchVolume": "200+",
      "started": "1 小時前"
    },
    {
      "googleTrend": "威力彩開獎號碼",
      "searchVolume": "200+",
      "started": "3 小時前"
    },
    {
      "googleTrend": "李德維",
      "searchVolume": "100+",
      "started": "1 小時前"
    },
    {
      "googleTrend": "mu",
      "searchVolume": "500+",
      "started": "3 小時前"
    }
  ]
}