{
  "updated": "2026-01-20T06:15:57.198Z",
  "trends": [
    {
      "googleTrend": "勇士 對 熱火",
      "searchVolume": "5,000+",
      "started": "3 小時前"
    },
    {
      "googleTrend": "米倉涼子",
      "searchVolume": "1,000+",
      "started": "2 小時前"
    },
    {
      "googleTrend": "阿蘇火山直升機",
      "searchVolume": "1,000+",
      "started": "30 分鐘前"
    },
    {
      "googleTrend": "趙少康",
      "searchVolume": "500+",
      "started": "3 小時前"
    },
    {
      "googleTrend": "jimmy butler",
      "searchVolume": "500+",
      "started": "50 分鐘前"
    },
    {
      "googleTrend": "磁暴",
      "searchVolume": "500+",
      "started": "1 小時前"
    },
    {
      "googleTrend": "貝克漢長子",
      "searchVolume": "500+",
      "started": "2 小時前"
    },
    {
      "googleTrend": "中興電",
      "searchVolume": "1,000+",
      "started": "3 小時前"
    },
    {
      "googleTrend": "2 小時前",
      "searchVolume": "500+",
      "started": "2 小時前"
    },
    {
      "googleTrend": "1 小時前",
      "searchVolume": "500+",
      "started": "1 小時前"
    },
    {
      "googleTrend": "1 小時前",
      "searchVolume": "200+",
      "started": "1 小時前"
    },
    {
      "googleTrend": "30 分鐘前",
      "searchVolume": "200+",
      "started": "30 分鐘前"
    },
    {
      "googleTrend": "皮蛇疫苗",
      "searchVolume": "200+",
      "started": "2 小時前"
    },
    {
      "googleTrend": "強茂",
      "searchVolume": "500+",
      "started": "3 小時前"
    },
    {
      "googleTrend": "nicola peltz",
      "searchVolume": "200+",
      "started": "1 小時前"
    },
    {
      "googleTrend": "紅白藝能大賞",
      "searchVolume": "100+",
      "started": "40 分鐘前"
    },
    {
      "googleTrend": "waymo",
      "searchVolume": "100+",
      "started": "20 分鐘前"
    },
    {
      "googleTrend": "康舒",
      "searchVolume": "500+",
      "started": "2 小時前"
    },
    {
      "googleTrend": "聯電",
      "searchVolume": "2,000+",
      "started": "3 小時前"
    },
    {
      "googleTrend": "單身即地獄 5",
      "searchVolume": "200+",
      "started": "1 小時前"
    },
    {
      "googleTrend": "川湖",
      "searchVolume": "200+",
      "started": "3 小時前"
    },
    {
      "googleTrend": "周滿芝",
      "searchVolume": "200+",
      "started": "1 小時前"
    },
    {
      "googleTrend": "關關",
      "searchVolume": "100+",
      "started": "1 小時前"
    },
    {
      "googleTrend": "超人力霸王",
      "searchVolume": "100+",
      "started": "1 小時前"
    },
    {
      "googleTrend": "寬宏",
      "searchVolume": "100+",
      "started": "1 小時前"
    }
  ]
}