{
  "updated": "2026-04-13T23:23:42.303Z",
  "trends": [
    {
      "googleTrend": "man utd đấu với leeds",
      "searchVolume": "500+",
      "started": "2 小時前"
    },
    {
      "googleTrend": "s&p 500",
      "searchVolume": "1,000+",
      "started": "2 小時前"
    },
    {
      "googleTrend": "曼聯 對 里茲聯",
      "searchVolume": "500+",
      "started": "3 小時前"
    },
    {
      "googleTrend": "man utd vs leeds",
      "searchVolume": "500+",
      "started": "3 小時前"
    },
    {
      "googleTrend": "แมนยู พบ ลีดส์",
      "searchVolume": "500+",
      "started": "3 小時前"
    },
    {
      "googleTrend": "費城半導體指數",
      "searchVolume": "1,000+",
      "started": "2 小時前"
    },
    {
      "googleTrend": "羅明才",
      "searchVolume": "100+",
      "started": "1 小時前"
    },
    {
      "googleTrend": "腦出血",
      "searchVolume": "200+",
      "started": "50 分鐘前"
    },
    {
      "googleTrend": "貪污",
      "searchVolume": "200+",
      "started": "1 小時前"
    },
    {
      "googleTrend": "華 邦 電",
      "searchVolume": "200+",
      "started": "1 小時前"
    },
    {
      "googleTrend": "黃光芹",
      "searchVolume": "100+",
      "started": "50 分鐘前"
    },
    {
      "googleTrend": "指數股票型基金",
      "searchVolume": "200+",
      "started": "10 分鐘前"
    },
    {
      "googleTrend": "道瓊工業平均指數",
      "searchVolume": "500+",
      "started": "1 小時前"
    },
    {
      "googleTrend": "那斯達克綜合指數",
      "searchVolume": "200+",
      "started": "2 小時前"
    },
    {
      "googleTrend": "intc",
      "searchVolume": "100+",
      "started": "1 小時前"
    },
    {
      "googleTrend": "orcl",
      "searchVolume": "100+",
      "started": "1 小時前"
    },
    {
      "googleTrend": "00919 配息",
      "searchVolume": "100+",
      "started": "10 分鐘前"
    },
    {
      "googleTrend": "淡江大橋",
      "searchVolume": "100+",
      "started": "1 小時前"
    },
    {
      "googleTrend": "英超",
      "searchVolume": "500+",
      "started": "3 小時前"
    },
    {
      "googleTrend": "mu",
      "searchVolume": "200+",
      "started": "1 小時前"
    }
  ]
}