{
  "updated": "2025-12-06T05:08:56.252Z",
  "trends": [
    {
      "googleTrend": "雷霆 對 獨行俠",
      "searchVolume": "2,000+",
      "started": "2 小時前"
    },
    {
      "googleTrend": "火箭 對 太陽",
      "searchVolume": "1,000+",
      "started": "3 小時前"
    },
    {
      "googleTrend": "世運",
      "searchVolume": "500+",
      "started": "2 小時前"
    },
    {
      "googleTrend": "公鹿 對 76人",
      "searchVolume": "500+",
      "started": "3 小時前"
    },
    {
      "googleTrend": "灰熊 對 快艇",
      "searchVolume": "500+",
      "started": "3 小時前"
    },
    {
      "googleTrend": "40 分鐘前",
      "searchVolume": "200+",
      "started": "40 分鐘前"
    },
    {
      "googleTrend": "高雄演唱會",
      "searchVolume": "200+",
      "started": "1 小時前"
    },
    {
      "googleTrend": "smx",
      "searchVolume": "200+",
      "started": "2 小時前"
    },
    {
      "googleTrend": "世運演唱會",
      "searchVolume": "100+",
      "started": "1 小時前"
    },
    {
      "googleTrend": "kpmg",
      "searchVolume": "100+",
      "started": "1 小時前"
    },
    {
      "googleTrend": "雷霆",
      "searchVolume": "100+",
      "started": "40 分鐘前"
    },
    {
      "googleTrend": "尼克 對 爵士",
      "searchVolume": "200+",
      "started": "3 小時前"
    },
    {
      "googleTrend": "應曉薇",
      "searchVolume": "200+",
      "started": "2 小時前"
    },
    {
      "googleTrend": "2 小時前",
      "searchVolume": "200+",
      "started": "2 小時前"
    },
    {
      "googleTrend": "簡煥宗",
      "searchVolume": "100+",
      "started": "2 小時前"
    },
    {
      "googleTrend": "9-10月發票中獎號碼",
      "searchVolume": "500+",
      "started": "3 小時前"
    },
    {
      "googleTrend": "吊車大王",
      "searchVolume": "100+",
      "started": "2 小時前"
    }
  ]
}