{
  "updated": "2026-03-10T11:46:11.592Z",
  "trends": [
    {
      "googleTrend": "jyp",
      "searchVolume": "2,000+",
      "started": "3 小時前"
    },
    {
      "googleTrend": "捷克日本",
      "searchVolume": "2,000+",
      "started": "2 小時前"
    },
    {
      "googleTrend": "satoria",
      "searchVolume": "1,000+",
      "started": "20 分鐘前"
    },
    {
      "googleTrend": "enhypen 李羲承",
      "searchVolume": "2,000+",
      "started": "3 小時前"
    },
    {
      "googleTrend": "麵屋一燈",
      "searchVolume": "500+",
      "started": "1 小時前"
    },
    {
      "googleTrend": "高橋宏斗",
      "searchVolume": "500+",
      "started": "3 小時前"
    },
    {
      "googleTrend": "曾豪駒",
      "searchVolume": "200+",
      "started": "1 小時前"
    },
    {
      "googleTrend": "華碩",
      "searchVolume": "500+",
      "started": "3 小時前"
    },
    {
      "googleTrend": "女足亞洲盃",
      "searchVolume": "200+",
      "started": "1 小時前"
    },
    {
      "googleTrend": "颱風",
      "searchVolume": "200+",
      "started": "1 小時前"
    },
    {
      "googleTrend": "cpbl",
      "searchVolume": "200+",
      "started": "30 分鐘前"
    },
    {
      "googleTrend": "台灣金聯平價住宅",
      "searchVolume": "100+",
      "started": "2 小時前"
    },
    {
      "googleTrend": "nhật bản đấu với việt nam",
      "searchVolume": "200+",
      "started": "2 小時前"
    },
    {
      "googleTrend": "橘色惡魔",
      "searchVolume": "100+",
      "started": "1 小時前"
    },
    {
      "googleTrend": "虎航股價",
      "searchVolume": "200+",
      "started": "3 小時前"
    },
    {
      "googleTrend": "日本地震",
      "searchVolume": "100+",
      "started": "3 小時前"
    },
    {
      "googleTrend": "中山",
      "searchVolume": "100+",
      "started": "2 小時前"
    },
    {
      "googleTrend": "停電",
      "searchVolume": "100+",
      "started": "1 小時前"
    },
    {
      "googleTrend": "保二",
      "searchVolume": "100+",
      "started": "2 小時前"
    },
    {
      "googleTrend": "qclaw",
      "searchVolume": "100+",
      "started": "3 小時前"
    }
  ]
}