{
  "updated": "2025-07-10T06:12:52.227Z",
  "trends": [
    {
      "googleTrend": "萬安演習時間",
      "searchVolume": "1,000+",
      "started": "1 小時前"
    },
    {
      "googleTrend": "台積電營收",
      "searchVolume": "200+",
      "started": "40 分鐘前"
    },
    {
      "googleTrend": "諾貝爾幼兒園",
      "searchVolume": "500+",
      "started": "1 小時前"
    },
    {
      "googleTrend": "我獨自升級",
      "searchVolume": "1,000+",
      "started": "3 小時前"
    },
    {
      "googleTrend": "grok 4",
      "searchVolume": "500+",
      "started": "2 小時前"
    },
    {
      "googleTrend": "t1",
      "searchVolume": "2,000+",
      "started": "2 小時前"
    },
    {
      "googleTrend": "李秀媛",
      "searchVolume": "100+",
      "started": "40 分鐘前"
    },
    {
      "googleTrend": "翁虹",
      "searchVolume": "100+",
      "started": "50 分鐘前"
    },
    {
      "googleTrend": "蕭文生",
      "searchVolume": "200+",
      "started": "1 小時前"
    },
    {
      "googleTrend": "沈慶京",
      "searchVolume": "100+",
      "started": "10 分鐘前"
    },
    {
      "googleTrend": "switch 2 價格",
      "searchVolume": "100+",
      "started": "1 小時前"
    },
    {
      "googleTrend": "台新金",
      "searchVolume": "200+",
      "started": "2 小時前"
    },
    {
      "googleTrend": "橋本環奈結婚",
      "searchVolume": "200+",
      "started": "2 小時前"
    },
    {
      "googleTrend": "kss火災",
      "searchVolume": "200+",
      "started": "2 小時前"
    },
    {
      "googleTrend": "苗栗建台高中",
      "searchVolume": "500+",
      "started": "3 小時前"
    },
    {
      "googleTrend": "geng",
      "searchVolume": "200+",
      "started": "2 小時前"
    },
    {
      "googleTrend": "玉山金",
      "searchVolume": "200+",
      "started": "3 小時前"
    },
    {
      "googleTrend": "地球自轉",
      "searchVolume": "200+",
      "started": "2 小時前"
    },
    {
      "googleTrend": "101",
      "searchVolume": "100+",
      "started": "1 小時前"
    },
    {
      "googleTrend": "馬國畢",
      "searchVolume": "100+",
      "started": "1 小時前"
    },
    {
      "googleTrend": "頂呱呱",
      "searchVolume": "100+",
      "started": "1 小時前"
    },
    {
      "googleTrend": "長榮航",
      "searchVolume": "100+",
      "started": "2 小時前"
    },
    {
      "googleTrend": "台燿",
      "searchVolume": "100+",
      "started": "3 小時前"
    },
    {
      "googleTrend": "東森",
      "searchVolume": "100+",
      "started": "3 小時前"
    }
  ]
}