{
  "updated": "2025-07-26T02:42:55.889Z",
  "trends": [
    {
      "googleTrend": "罷免開票",
      "searchVolume": "2,000+",
      "started": "3 小時前"
    },
    {
      "googleTrend": "投票地點",
      "searchVolume": "1,000+",
      "started": "3 小時前"
    },
    {
      "googleTrend": "開票",
      "searchVolume": "200+",
      "started": "1 小時前"
    },
    {
      "googleTrend": "投票所",
      "searchVolume": "500+",
      "started": "3 小時前"
    },
    {
      "googleTrend": "丁彥宸",
      "searchVolume": "200+",
      "started": "1 小時前"
    },
    {
      "googleTrend": "網紅女警",
      "searchVolume": "1,000+",
      "started": "3 小時前"
    },
    {
      "googleTrend": "洪孟楷",
      "searchVolume": "200+",
      "started": "2 小時前"
    },
    {
      "googleTrend": "世貿一館",
      "searchVolume": "200+",
      "started": "2 小時前"
    },
    {
      "googleTrend": "王鴻薇",
      "searchVolume": "500+",
      "started": "1 小時前"
    },
    {
      "googleTrend": "國道逆向",
      "searchVolume": "200+",
      "started": "1 小時前"
    },
    {
      "googleTrend": "呂玉玲",
      "searchVolume": "200+",
      "started": "2 小時前"
    },
    {
      "googleTrend": "選舉",
      "searchVolume": "200+",
      "started": "2 小時前"
    },
    {
      "googleTrend": "國防醫學院",
      "searchVolume": "200+",
      "started": "3 小時前"
    },
    {
      "googleTrend": "紅襪 對 道奇",
      "searchVolume": "200+",
      "started": "1 小時前"
    },
    {
      "googleTrend": "松菸",
      "searchVolume": "200+",
      "started": "30 分鐘前"
    },
    {
      "googleTrend": "投票日",
      "searchVolume": "100+",
      "started": "2 小時前"
    },
    {
      "googleTrend": "涂權吉",
      "searchVolume": "100+",
      "started": "2 小時前"
    },
    {
      "googleTrend": "蔡允潔",
      "searchVolume": "200+",
      "started": "3 小時前"
    },
    {
      "googleTrend": "mlb直播",
      "searchVolume": "200+",
      "started": "3 小時前"
    },
    {
      "googleTrend": "洋基",
      "searchVolume": "200+",
      "started": "3 小時前"
    }
  ]
}