{
  "updated": "2025-12-03T01:37:34.231Z",
  "trends": [
    {
      "googleTrend": "台灣保證實施法案",
      "searchVolume": "500+",
      "started": "20 分鐘前"
    },
    {
      "googleTrend": "林書逸",
      "searchVolume": "500+",
      "started": "1 小時前"
    },
    {
      "googleTrend": "越洋航空",
      "searchVolume": "500+",
      "started": "1 小時前"
    },
    {
      "googleTrend": "馬刺 對 灰熊",
      "searchVolume": "200+",
      "started": "30 分鐘前"
    },
    {
      "googleTrend": "世芯",
      "searchVolume": "500+",
      "started": "20 分鐘前"
    },
    {
      "googleTrend": "塞爾提克 對 尼克",
      "searchVolume": "200+",
      "started": "20 分鐘前"
    },
    {
      "googleTrend": "鵜鶘 對 灰狼",
      "searchVolume": "200+",
      "started": "20 分鐘前"
    },
    {
      "googleTrend": "傳說對決",
      "searchVolume": "200+",
      "started": "1 小時前"
    },
    {
      "googleTrend": "定穎投控",
      "searchVolume": "200+",
      "started": "20 分鐘前"
    },
    {
      "googleTrend": "1303",
      "searchVolume": "200+",
      "started": "10 分鐘前"
    },
    {
      "googleTrend": "中油",
      "searchVolume": "500+",
      "started": "2 小時前"
    },
    {
      "googleTrend": "張軒睿",
      "searchVolume": "100+",
      "started": "10 分鐘前"
    },
    {
      "googleTrend": "jal",
      "searchVolume": "100+",
      "started": "40 分鐘前"
    },
    {
      "googleTrend": "亞電",
      "searchVolume": "100+",
      "started": "20 分鐘前"
    },
    {
      "googleTrend": "ipass money",
      "searchVolume": "500+",
      "started": "2 小時前"
    },
    {
      "googleTrend": "台虹",
      "searchVolume": "100+",
      "started": "10 分鐘前"
    },
    {
      "googleTrend": "台中銀",
      "searchVolume": "100+",
      "started": "30 分鐘前"
    },
    {
      "googleTrend": "許莉廷",
      "searchVolume": "100+",
      "started": "20 分鐘前"
    },
    {
      "googleTrend": "fulham vs man city",
      "searchVolume": "200+",
      "started": "3 小時前"
    },
    {
      "googleTrend": "fulham đấu với man city",
      "searchVolume": "200+",
      "started": "3 小時前"
    },
    {
      "googleTrend": "barcelona đấu với atlético madrid",
      "searchVolume": "200+",
      "started": "3 小時前"
    },
    {
      "googleTrend": "newcastle vs tottenham",
      "searchVolume": "200+",
      "started": "2 小時前"
    },
    {
      "googleTrend": "紐卡索聯 對 熱刺",
      "searchVolume": "200+",
      "started": "2 小時前"
    },
    {
      "googleTrend": "ฟูลัม พบ แมนซิตี",
      "searchVolume": "200+",
      "started": "3 小時前"
    },
    {
      "googleTrend": "職業安全衛生法",
      "searchVolume": "100+",
      "started": "30 分鐘前"
    }
  ]
}