{
  "updated": "2026-05-02T18:52:02.416Z",
  "trends": [
    {
      "googleTrend": "3 小時前",
      "searchVolume": "200+",
      "started": "3 小時前"
    },
    {
      "googleTrend": "alex zanardi",
      "searchVolume": "200+",
      "started": "3 小時前"
    },
    {
      "googleTrend": "f1直播",
      "searchVolume": "200+",
      "started": "2 小時前"
    },
    {
      "googleTrend": "f1 邁阿密",
      "searchVolume": "100+",
      "started": "2 小時前"
    },
    {
      "googleTrend": "戶田惠梨香",
      "searchVolume": "200+",
      "started": "3 小時前"
    },
    {
      "googleTrend": "海底電纜",
      "searchVolume": "100+",
      "started": "2 小時前"
    },
    {
      "googleTrend": "psg vs lorient",
      "searchVolume": "100+",
      "started": "3 小時前"
    },
    {
      "googleTrend": "鄭運鵬",
      "searchVolume": "100+",
      "started": "2 小時前"
    },
    {
      "googleTrend": "disney+",
      "searchVolume": "200+",
      "started": "3 小時前"
    }
  ]
}