{
  "updated": "2025-12-20T08:53:10.769Z",
  "trends": [
    {
      "replyCount": 91,
      "date": "2025/12/20",
      "time": "00:00",
      "title": "無題",
      "description": "無本文",
      "link": "https://gita.komica1.org/00b/pixmicat.php?res=29385601",
      "rawText": "91|29385601|2025/12/20|00:00|無題|無本文|在新分頁開啟"
    },
    {
      "replyCount": 85,
      "date": "2025/12/20",
      "time": "12:21",
      "title": "無題",
      "description": "其實這時機不去阻止真的很可惜因為煙幕彈殺",
      "link": "https://gita.komica1.org/00b/pixmicat.php?res=29391204",
      "rawText": "85|29391204|2025/12/20|12:21|無題|其實這時機不去阻止真的很可惜因為煙幕彈殺|在新分頁開啟"
    },
    {
      "replyCount": 64,
      "date": "2025/12/20",
      "time": "10:13",
      "title": "無題",
      "description": "蔣公子被看沒有",
      "link": "https://gita.komica1.org/00b/pixmicat.php?res=29390185",
      "rawText": "64|29390185|2025/12/20|10:13|無題|蔣公子被看沒有|在新分頁開啟"
    },
    {
      "replyCount": 62,
      "date": "2025/12/20",
      "time": "09:00",
      "title": "無題",
      "description": "1.「張文」有YT頻道，拼音是中國拼法z",
      "link": "https://gita.komica1.org/00b/pixmicat.php?res=29389694",
      "rawText": "62|29389694|2025/12/20|09:00|無題|1.「張文」有YT頻道，拼音是中國拼法z|在新分頁開啟"
    },
    {
      "replyCount": 50,
      "date": "2025/12/20",
      "time": "11:05",
      "title": "無題",
      "description": "一臉島樣",
      "link": "https://gita.komica1.org/00b/pixmicat.php?res=29390586",
      "rawText": "50|29390586|2025/12/20|11:05|無題|一臉島樣|在新分頁開啟"
    },
    {
      "replyCount": 50,
      "date": "2025/12/20",
      "time": "12:50",
      "title": "無題",
      "description": "現在瘋傳美網，美國網友對於台灣人只會站在",
      "link": "https://gita.komica1.org/00b/pixmicat.php?res=29391416",
      "rawText": "50|29391416|2025/12/20|12:50|無題|現在瘋傳美網，美國網友對於台灣人只會站在|在新分頁開啟"
    },
    {
      "replyCount": 45,
      "date": "2025/12/20",
      "time": "08:13",
      "title": "無題",
      "description": "好想在上班前對這樣的女生盡情撒嬌喔!好想",
      "link": "https://gita.komica1.org/00b/pixmicat.php?res=29389509",
      "rawText": "45|29389509|2025/12/20|08:13|無題|好想在上班前對這樣的女生盡情撒嬌喔!好想|在新分頁開啟"
    },
    {
      "replyCount": 44,
      "date": "2025/12/20",
      "time": "00:00",
      "title": "女角",
      "description": "無本文",
      "link": "https://gita.komica1.org/00b/pixmicat.php?res=29380910",
      "rawText": "44|29380910|2025/12/20|00:00|女角|無本文|在新分頁開啟"
    },
    {
      "replyCount": 43,
      "date": "2025/12/20",
      "time": "11:14",
      "title": "無題",
      "description": "宅男哀歌...",
      "link": "https://gita.komica1.org/00b/pixmicat.php?res=29390669",
      "rawText": "43|29390669|2025/12/20|11:14|無題|宅男哀歌...|在新分頁開啟"
    },
    {
      "replyCount": 40,
      "date": "2025/12/20",
      "time": "09:50",
      "title": "無題",
      "description": "張文爸很像深藍的阿北",
      "link": "https://gita.komica1.org/00b/pixmicat.php?res=29390019",
      "rawText": "40|29390019|2025/12/20|09:50|無題|張文爸很像深藍的阿北|在新分頁開啟"
    },
    {
      "replyCount": 39,
      "date": "2025/12/20",
      "time": "07:40",
      "title": "無題",
      "description": "不是啊北捷已經經歷過鄭捷的事件不是應該對",
      "link": "https://gita.komica1.org/00b/pixmicat.php?res=29389406",
      "rawText": "39|29389406|2025/12/20|07:40|無題|不是啊北捷已經經歷過鄭捷的事件不是應該對|在新分頁開啟"
    },
    {
      "replyCount": 39,
      "date": "2025/12/20",
      "time": "09:54",
      "title": "如果今天是你遇到影片這種情況你會怎麼做？",
      "description": "這樣做有效嗎？",
      "link": "https://gita.komica1.org/00b/pixmicat.php?res=29390040",
      "rawText": "39|29390040|2025/12/20|09:54|如果今天是你遇到影片這種情況你會怎麼做？|這樣做有效嗎？|在新分頁開啟"
    },
    {
      "replyCount": 35,
      "date": "2025/12/20",
      "time": "06:14",
      "title": "無題",
      "description": "島島大問答Q:遇到通緝犯張文當街持刀隨機",
      "link": "https://gita.komica1.org/00b/pixmicat.php?res=29389231",
      "rawText": "35|29389231|2025/12/20|06:14|無題|島島大問答Q:遇到通緝犯張文當街持刀隨機|在新分頁開啟"
    },
    {
      "replyCount": 35,
      "date": "2025/12/20",
      "time": "09:37",
      "title": "無題",
      "description": "無本文",
      "link": "https://gita.komica1.org/00b/pixmicat.php?res=29389907",
      "rawText": "35|29389907|2025/12/20|09:37|無題|無本文|在新分頁開啟"
    },
    {
      "replyCount": 35,
      "date": "2025/12/20",
      "time": "12:45",
      "title": "無題",
      "description": "拿步槍這樣算挑釁第五縱隊嗎?",
      "link": "https://gita.komica1.org/00b/pixmicat.php?res=29391392",
      "rawText": "35|29391392|2025/12/20|12:45|無題|拿步槍這樣算挑釁第五縱隊嗎?|在新分頁開啟"
    },
    {
      "replyCount": 34,
      "date": "2025/12/20",
      "time": "08:01",
      "title": "無題",
      "description": "信仰之躍？",
      "link": "https://gita.komica1.org/00b/pixmicat.php?res=29389467",
      "rawText": "34|29389467|2025/12/20|08:01|無題|信仰之躍？|在新分頁開啟"
    },
    {
      "replyCount": 33,
      "date": "2025/12/20",
      "time": "01:48",
      "title": "無題",
      "description": "這就是為什麼不要想空手去對付有武器的人",
      "link": "https://gita.komica1.org/00b/pixmicat.php?res=29387573",
      "rawText": "33|29387573|2025/12/20|01:48|無題|這就是為什麼不要想空手去對付有武器的人|在新分頁開啟"
    },
    {
      "replyCount": 33,
      "date": "2025/12/20",
      "time": "02:27",
      "title": "無題",
      "description": "管太多說不定還嫌矯枉過正",
      "link": "https://gita.komica1.org/00b/pixmicat.php?res=29388915",
      "rawText": "33|29388915|2025/12/20|02:27|無題|管太多說不定還嫌矯枉過正|在新分頁開啟"
    },
    {
      "replyCount": 32,
      "date": "2025/12/20",
      "time": "14:12",
      "title": "無題",
      "description": "台北市昨天發生隨機殺人案造成嚴重傷亡，目",
      "link": "https://gita.komica1.org/00b/pixmicat.php?res=29392031",
      "rawText": "32|29392031|2025/12/20|14:12|無題|台北市昨天發生隨機殺人案造成嚴重傷亡，目|在新分頁開啟"
    },
    {
      "replyCount": 31,
      "date": "2025/12/20",
      "time": "12:06",
      "title": "怎麼常有人說他自己被BAN鎖IP阿？",
      "description": "是真的有這回事？還是喊好玩的？因為如果被",
      "link": "https://gita.komica1.org/00b/pixmicat.php?res=29391085",
      "rawText": "31|29391085|2025/12/20|12:06|怎麼常有人說他自己被BAN鎖IP阿？|是真的有這回事？還是喊好玩的？因為如果被|在新分頁開啟"
    },
    {
      "replyCount": 29,
      "date": "2025/12/20",
      "time": "09:24",
      "title": "無題",
      "description": "台灣人經過這次事件後還會覺得民防不重要嗎",
      "link": "https://gita.komica1.org/00b/pixmicat.php?res=29389828",
      "rawText": "29|29389828|2025/12/20|09:24|無題|台灣人經過這次事件後還會覺得民防不重要嗎|在新分頁開啟"
    },
    {
      "replyCount": 28,
      "date": "2025/12/20",
      "time": "13:07",
      "title": "你齁又出事了",
      "description": "這次是你齁那狀況百出的六期名義上的總帥出",
      "link": "https://gita.komica1.org/00b/pixmicat.php?res=29391557",
      "rawText": "28|29391557|2025/12/20|13:07|你齁又出事了|這次是你齁那狀況百出的六期名義上的總帥出|在新分頁開啟"
    },
    {
      "replyCount": 27,
      "date": "2025/12/20",
      "time": "00:31",
      "title": "無題",
      "description": "怎麼這麼巧連續兩次在台北的重大治安事件嫌",
      "link": "https://gita.komica1.org/00b/pixmicat.php?res=29388495",
      "rawText": "27|29388495|2025/12/20|00:31|無題|怎麼這麼巧連續兩次在台北的重大治安事件嫌|在新分頁開啟"
    },
    {
      "replyCount": 27,
      "date": "2025/12/20",
      "time": "14:21",
      "title": "無題",
      "description": "獨／隨機殺人傷者為愛滋感染者衛福部14時",
      "link": "https://gita.komica1.org/00b/pixmicat.php?res=29392103",
      "rawText": "27|29392103|2025/12/20|14:21|無題|獨／隨機殺人傷者為愛滋感染者衛福部14時|在新分頁開啟"
    },
    {
      "replyCount": 26,
      "date": "2025/12/20",
      "time": "10:40",
      "title": "無題",
      "description": "誠品南西店有員工透露張文墜樓的頂樓之前堆",
      "link": "https://gita.komica1.org/00b/pixmicat.php?res=29390386",
      "rawText": "26|29390386|2025/12/20|10:40|無題|誠品南西店有員工透露張文墜樓的頂樓之前堆|在新分頁開啟"
    },
    {
      "replyCount": 26,
      "date": "2025/12/20",
      "time": "11:42",
      "title": "無題",
      "description": "有沒有高學歷高智商的人玩隨機殺人看膩了那",
      "link": "https://gita.komica1.org/00b/pixmicat.php?res=29390918",
      "rawText": "26|29390918|2025/12/20|11:42|無題|有沒有高學歷高智商的人玩隨機殺人看膩了那|在新分頁開啟"
    },
    {
      "replyCount": 26,
      "date": "2025/12/20",
      "time": "14:07",
      "title": "惡靈古堡系列",
      "description": "這系列該怎麼入門?從來沒玩過這系列一大堆",
      "link": "https://gita.komica1.org/00b/pixmicat.php?res=29391984",
      "rawText": "26|29391984|2025/12/20|14:07|惡靈古堡系列|這系列該怎麼入門?從來沒玩過這系列一大堆|在新分頁開啟"
    },
    {
      "replyCount": 25,
      "date": "2025/12/20",
      "time": "11:18",
      "title": "無題",
      "description": "唉沒想到台灣變成這樣準備買一件防刺的立領",
      "link": "https://gita.komica1.org/00b/pixmicat.php?res=29390705",
      "rawText": "25|29390705|2025/12/20|11:18|無題|唉沒想到台灣變成這樣準備買一件防刺的立領|在新分頁開啟"
    },
    {
      "replyCount": 25,
      "date": "2025/12/20",
      "time": "14:33",
      "title": "無題",
      "description": "處理詐騙的解答就在眼前但台灣連抄答案都做",
      "link": "https://gita.komica1.org/00b/pixmicat.php?res=29392189",
      "rawText": "25|29392189|2025/12/20|14:33|無題|處理詐騙的解答就在眼前但台灣連抄答案都做|在新分頁開啟"
    },
    {
      "replyCount": 25,
      "date": "2025/12/20",
      "time": "15:42",
      "title": "無題",
      "description": "幹蝦仁看太多突然覺得日本動畫的裝逼都超難",
      "link": "https://gita.komica1.org/00b/pixmicat.php?res=29392574",
      "rawText": "25|29392574|2025/12/20|15:42|無題|幹蝦仁看太多突然覺得日本動畫的裝逼都超難|在新分頁開啟"
    },
    {
      "replyCount": 24,
      "date": "2025/12/20",
      "time": "10:39",
      "title": "憲法法庭復活！國民黨團：下週一告發大法官",
      "description": "https://www.nownews.",
      "link": "https://gita.komica1.org/00b/pixmicat.php?res=29390338",
      "rawText": "24|29390338|2025/12/20|10:39|憲法法庭復活！國民黨團：下週一告發大法官|https://www.nownews.|在新分頁開啟"
    },
    {
      "replyCount": 24,
      "date": "2025/12/20",
      "time": "12:08",
      "title": "無題",
      "description": "北捷隨機砍人兇嫌張文曾就讀桃園永平工商同",
      "link": "https://gita.komica1.org/00b/pixmicat.php?res=29391025",
      "rawText": "24|29391025|2025/12/20|12:08|無題|北捷隨機砍人兇嫌張文曾就讀桃園永平工商同|在新分頁開啟"
    },
    {
      "replyCount": 23,
      "date": "2025/12/20",
      "time": "00:06",
      "title": "無題",
      "description": "第三個應該是前面島民貼的影片中騎機車被劃",
      "link": "https://gita.komica1.org/00b/pixmicat.php?res=29387062",
      "rawText": "23|29387062|2025/12/20|00:06|無題|第三個應該是前面島民貼的影片中騎機車被劃|在新分頁開啟"
    },
    {
      "replyCount": 23,
      "date": "2025/12/20",
      "time": "00:01",
      "title": "無題",
      "description": "為什麼他會認為嫌犯若是第五縱隊會讓藍白背",
      "link": "https://gita.komica1.org/00b/pixmicat.php?res=29388250",
      "rawText": "23|29388250|2025/12/20|00:01|無題|為什麼他會認為嫌犯若是第五縱隊會讓藍白背|在新分頁開啟"
    },
    {
      "replyCount": 23,
      "date": "2025/12/20",
      "time": "09:45",
      "title": "無題",
      "description": "連公子說這句是不是自打嘴巴?",
      "link": "https://gita.komica1.org/00b/pixmicat.php?res=29389984",
      "rawText": "23|29389984|2025/12/20|09:45|無題|連公子說這句是不是自打嘴巴?|在新分頁開啟"
    },
    {
      "replyCount": 22,
      "date": "2025/12/20",
      "time": "10:34",
      "title": "無題",
      "description": "台灣應該立法前膛槍合法化黑熊部隊跟民防隊",
      "link": "https://gita.komica1.org/00b/pixmicat.php?res=29390352",
      "rawText": "22|29390352|2025/12/20|10:34|無題|台灣應該立法前膛槍合法化黑熊部隊跟民防隊|在新分頁開啟"
    },
    {
      "replyCount": 22,
      "date": "2025/12/20",
      "time": "11:48",
      "title": "無題",
      "description": "感受到中國人的溫暖統一似乎也沒有不好吧",
      "link": "https://gita.komica1.org/00b/pixmicat.php?res=29390958",
      "rawText": "22|29390958|2025/12/20|11:48|無題|感受到中國人的溫暖統一似乎也沒有不好吧|在新分頁開啟"
    },
    {
      "replyCount": 22,
      "date": "2025/12/20",
      "time": "13:34",
      "title": "無題",
      "description": "為什麼台灣人只聽老歌?連日本歌排行榜也都",
      "link": "https://gita.komica1.org/00b/pixmicat.php?res=29391737",
      "rawText": "22|29391737|2025/12/20|13:34|無題|為什麼台灣人只聽老歌?連日本歌排行榜也都|在新分頁開啟"
    },
    {
      "replyCount": 21,
      "date": "2025/12/20",
      "time": "10:16",
      "title": "無題",
      "description": "島民覺得會出現隨機殺人犯是家庭的錯還是社",
      "link": "https://gita.komica1.org/00b/pixmicat.php?res=29390233",
      "rawText": "21|29390233|2025/12/20|10:16|無題|島民覺得會出現隨機殺人犯是家庭的錯還是社|在新分頁開啟"
    },
    {
      "replyCount": 21,
      "date": "2025/12/20",
      "time": "12:16",
      "title": "無題",
      "description": "世界什麼時候跟上秘魯",
      "link": "https://gita.komica1.org/00b/pixmicat.php?res=29391161",
      "rawText": "21|29391161|2025/12/20|12:16|無題|世界什麼時候跟上秘魯|在新分頁開啟"
    },
    {
      "replyCount": 21,
      "date": "2025/12/20",
      "time": "13:38",
      "title": "無題",
      "description": "不是只有出張嘴讓警察出來加班自己也親自巡",
      "link": "https://gita.komica1.org/00b/pixmicat.php?res=29391764",
      "rawText": "21|29391764|2025/12/20|13:38|無題|不是只有出張嘴讓警察出來加班自己也親自巡|在新分頁開啟"
    },
    {
      "replyCount": 20,
      "date": "2025/12/20",
      "time": "00:07",
      "title": "無題",
      "description": "島民可以幫我看看我到底說錯什麼才會被管理",
      "link": "https://gita.komica1.org/00b/pixmicat.php?res=29386916",
      "rawText": "20|29386916|2025/12/20|00:07|無題|島民可以幫我看看我到底說錯什麼才會被管理|在新分頁開啟"
    },
    {
      "replyCount": 20,
      "date": "2025/12/20",
      "time": "00:30",
      "title": "無題",
      "description": "無本文",
      "link": "https://gita.komica1.org/00b/pixmicat.php?res=29388500",
      "rawText": "20|29388500|2025/12/20|00:30|無題|無本文|在新分頁開啟"
    },
    {
      "replyCount": 20,
      "date": "2025/12/20",
      "time": "13:10",
      "title": "無題",
      "description": "只能選一隻瘋狂種付",
      "link": "https://gita.komica1.org/00b/pixmicat.php?res=29391588",
      "rawText": "20|29391588|2025/12/20|13:10|無題|只能選一隻瘋狂種付|在新分頁開啟"
    },
    {
      "replyCount": 20,
      "date": "2025/12/20",
      "time": "13:33",
      "title": "無題",
      "description": "為什麼要歧視中配害張文去砍人藍白的腦真的",
      "link": "https://gita.komica1.org/00b/pixmicat.php?res=29391746",
      "rawText": "20|29391746|2025/12/20|13:33|無題|為什麼要歧視中配害張文去砍人藍白的腦真的|在新分頁開啟"
    },
    {
      "replyCount": 19,
      "date": "2025/12/20",
      "time": "03:57",
      "title": "幹...確定是孤狼式恐怖攻擊了...",
      "description": "確定是孤狼式恐怖攻擊還好台灣禁槍不然如果",
      "link": "https://gita.komica1.org/00b/pixmicat.php?res=29385790",
      "rawText": "19|29385790|2025/12/20|03:57|幹...確定是孤狼式恐怖攻擊了...|確定是孤狼式恐怖攻擊還好台灣禁槍不然如果|在新分頁開啟"
    },
    {
      "replyCount": 19,
      "date": "2025/12/20",
      "time": "00:00",
      "title": "無題",
      "description": "看到脆一堆人在說民進黨執政治安差菜逼巴真",
      "link": "https://gita.komica1.org/00b/pixmicat.php?res=29387928",
      "rawText": "19|29387928|2025/12/20|00:00|無題|看到脆一堆人在說民進黨執政治安差菜逼巴真|在新分頁開啟"
    },
    {
      "replyCount": 19,
      "date": "2025/12/20",
      "time": "06:21",
      "title": "無題",
      "description": "一群犯罪預備軍",
      "link": "https://gita.komica1.org/00b/pixmicat.php?res=29389235",
      "rawText": "19|29389235|2025/12/20|06:21|無題|一群犯罪預備軍|在新分頁開啟"
    },
    {
      "replyCount": 19,
      "date": "2025/12/20",
      "time": "10:11",
      "title": "無題",
      "description": "日本的酒店小姐都漂亮又有氣質...反觀台",
      "link": "https://gita.komica1.org/00b/pixmicat.php?res=29390175",
      "rawText": "19|29390175|2025/12/20|10:11|無題|日本的酒店小姐都漂亮又有氣質...反觀台|在新分頁開啟"
    },
    {
      "replyCount": 19,
      "date": "2025/12/20",
      "time": "10:22",
      "title": "這部當初怎麼會那麼紅阿",
      "description": "這種題材以前不常見嗎？https://y",
      "link": "https://gita.komica1.org/00b/pixmicat.php?res=29390279",
      "rawText": "19|29390279|2025/12/20|10:22|這部當初怎麼會那麼紅阿|這種題材以前不常見嗎？https://y|在新分頁開啟"
    }
  ]
}