{
  "updated": "2026-03-03T19:11:21.475Z",
  "total_found": 20,
  "returned_count": 20,
  "articles": [
    {
      "recommendScore": "246",
      "recommendCount": "938",
      "title": "[新聞] 拒絕被矮化！南韓電子入境卡列「中國台灣」外交部出招了",
      "link": "/bbs/Gossiping/M.1772530377.A.CD0",
      "author": "the06512",
      "board": "Gossiping",
      "publishTime": "2026/03/03 09:32",
      "imageUrl": ""
    },
    {
      "recommendScore": "365",
      "recommendCount": "653",
      "title": "[新聞] 王定宇奪人小三／獨家直擊！頻繁夜渡名媛小三香閨　王定宇再爆外遇",
      "link": "/bbs/Gossiping/M.1772498906.A.54F",
      "author": "CF661020",
      "board": "Gossiping",
      "publishTime": "2026/03/03 00:48",
      "imageUrl": ""
    },
    {
      "recommendScore": "272",
      "recommendCount": "622",
      "title": "[新聞] 王定宇喊已離婚！妻PO文「不哭不哭…」一夜變單身了",
      "link": "/bbs/Gossiping/M.1772504171.A.FD2",
      "author": "Kazmier",
      "board": "Gossiping",
      "publishTime": "2026/03/03 02:16",
      "imageUrl": ""
    },
    {
      "recommendScore": "281",
      "recommendCount": "552",
      "title": "[外絮] 咖哩和嘴綠今年休賽季將全力招募LBJ",
      "link": "/bbs/NBA/M.1772496436.A.CDB",
      "author": "Wojnarowski",
      "board": "NBA",
      "publishTime": "2026/03/03 00:07",
      "imageUrl": ""
    },
    {
      "recommendScore": "150",
      "recommendCount": "436",
      "title": "[新聞] 美伊戰爭台股有韌性！謝金河點名7台廠市值逾1兆　成投資定海神針",
      "link": "/bbs/Stock/M.1772514723.A.CA9",
      "author": "sexybox",
      "board": "Stock",
      "publishTime": "2026/03/03 05:12",
      "imageUrl": ""
    },
    {
      "recommendScore": "200",
      "recommendCount": "450",
      "title": "[新聞] 快訊／台股跌771點國安基金進場？　卓榮泰回應！",
      "link": "/bbs/Stock/M.1772527785.A.C34",
      "author": "ChanHoPark",
      "board": "Stock",
      "publishTime": "2026/03/03 08:49",
      "imageUrl": ""
    },
    {
      "recommendScore": "227",
      "recommendCount": "450",
      "title": "[新聞] 王定宇惹桃色風暴 傳民進黨中評會要拔他中常委",
      "link": "/bbs/Gossiping/M.1772523031.A.471",
      "author": "pp5270",
      "board": "Gossiping",
      "publishTime": "2026/03/03 07:30",
      "imageUrl": ""
    },
    {
      "recommendScore": "241",
      "recommendCount": "364",
      "title": "[討論] 各位看完熱身賽的感想如何",
      "link": "/bbs/Baseball/M.1772512549.A.3AB",
      "author": "jeff95123",
      "board": "Baseball",
      "publishTime": "2026/03/03 04:35",
      "imageUrl": ""
    },
    {
      "recommendScore": "209",
      "recommendCount": "888",
      "title": "[新聞] 員警沒洗車 基隆所長洗完手指抹車牌吸吮惹議",
      "link": "/bbs/Gossiping/M.1772489513.A.AB7",
      "author": "JKGOOD",
      "board": "Gossiping",
      "publishTime": "2026/03/02 22:11",
      "imageUrl": ""
    },
    {
      "recommendScore": "181",
      "recommendCount": "328",
      "title": "[問卦] 為什麼一堆人還去王八千臉書加油",
      "link": "/bbs/Gossiping/M.1772509127.A.2C8",
      "author": "peanut0823",
      "board": "Gossiping",
      "publishTime": "2026/03/03 03:38",
      "imageUrl": ""
    },
    {
      "recommendScore": "181",
      "recommendCount": "385",
      "title": "[情報] 川普：美軍彈藥充足且優質，可「永遠打下",
      "link": "/bbs/Stock/M.1772516727.A.35A",
      "author": "komeko",
      "board": "Stock",
      "publishTime": "2026/03/03 05:45",
      "imageUrl": ""
    },
    {
      "recommendScore": "159",
      "recommendCount": "350",
      "title": "[新聞] 王定宇「搶小三」回應了！嚴正駁斥：已離婚",
      "link": "/bbs/Gossiping/M.1772499740.A.284",
      "author": "karta328",
      "board": "Gossiping",
      "publishTime": "2026/03/03 01:02",
      "imageUrl": ""
    },
    {
      "recommendScore": "179",
      "recommendCount": "324",
      "title": "[新聞] 賴瑞隆又出包！把幕僚建議內容貼在臉書",
      "link": "/bbs/Gossiping/M.1772533096.A.CB7",
      "author": "Ezimet",
      "board": "Gossiping",
      "publishTime": "2026/03/03 10:18",
      "imageUrl": ""
    },
    {
      "recommendScore": "161",
      "recommendCount": "324",
      "title": "[新聞] 「E級名媛」劉怡萱情史超狂！大學同學認證：被她盯上的都會暈",
      "link": "/bbs/Gossiping/M.1772525057.A.80C",
      "author": "cosmite",
      "board": "Gossiping",
      "publishTime": "2026/03/03 08:04",
      "imageUrl": "https://cache.pttweb.cc/imgur/663ZWfL/s/6239d173d983bca8ea4f5d6edbe5528c"
    },
    {
      "recommendScore": "222",
      "recommendCount": "285",
      "title": "[炸裂] 金倒永",
      "link": "/bbs/Baseball/M.1772508801.A.329",
      "author": "Neoooooo",
      "board": "Baseball",
      "publishTime": "2026/03/03 03:33",
      "imageUrl": ""
    },
    {
      "recommendScore": "167",
      "recommendCount": "357",
      "title": "[新聞] 快訊／美國急發「大規模撤離令」橫跨10餘國！　德派專機撤僑",
      "link": "/bbs/Gossiping/M.1772496928.A.5E4",
      "author": "STi2011",
      "board": "Gossiping",
      "publishTime": "2026/03/03 00:15",
      "imageUrl": ""
    },
    {
      "recommendScore": "173",
      "recommendCount": "306",
      "title": "[請益] 這時候是不是應該要慢慢進場了",
      "link": "/bbs/Stock/M.1772543832.A.60F",
      "author": "hong1126",
      "board": "Stock",
      "publishTime": "2026/03/03 13:17",
      "imageUrl": ""
    },
    {
      "recommendScore": "163",
      "recommendCount": "348",
      "title": "[問卦] “錯誤的政策比貪污更可怕”，能舉個例",
      "link": "/bbs/Gossiping/M.1772495855.A.DE0",
      "author": "zakijudelo",
      "board": "Gossiping",
      "publishTime": "2026/03/02 23:57",
      "imageUrl": ""
    },
    {
      "recommendScore": "233",
      "recommendCount": "245",
      "title": "Re: [LIVE] 亞冠 武里南聯@墨爾本城 場中",
      "link": "/bbs/SportLottery/M.1772531066.A.EE7",
      "author": "b032819",
      "board": "SportLottery",
      "publishTime": "2026/03/03 09:44",
      "imageUrl": ""
    },
    {
      "recommendScore": "128",
      "recommendCount": "318",
      "title": "[新聞] 爆黃國昌被開5張搜索票 柯文哲怒喊別再搞他：再用政治手段我一定焦土政策",
      "link": "/bbs/Gossiping/M.1772519618.A.595",
      "author": "postar",
      "board": "Gossiping",
      "publishTime": "2026/03/03 06:33",
      "imageUrl": ""
    }
  ]
}