{
  "updated": "2026-01-27T16:44:19.077Z",
  "total_found": 20,
  "returned_count": 20,
  "articles": [
    {
      "recommendScore": "105",
      "recommendCount": "203",
      "title": "[新聞] 快訊／第十度卡關！　藍白拒審中央政府總預算、1.25兆國防特別條例",
      "link": "/bbs/Gossiping/M.1769490023.A.88B",
      "author": "seiya2000",
      "board": "Gossiping",
      "publishTime": "2026/01/27 05:00",
      "imageUrl": ""
    },
    {
      "recommendScore": "63",
      "recommendCount": "98",
      "title": "[閒聊] 微軟公佈GTA6容量為676G",
      "link": "/bbs/C_Chat/M.1769511409.A.611",
      "author": "peterboon",
      "board": "C_Chat",
      "publishTime": "2026/01/27 10:56",
      "imageUrl": ""
    },
    {
      "recommendScore": "72",
      "recommendCount": "165",
      "title": "[問題] 你覺得器官買賣是真的？（政治1/1）",
      "link": "/bbs/BaseballXXXX/M.1769507221.A.39E",
      "author": "ysb727",
      "board": "BaseballXXXX",
      "publishTime": "2026/01/27 09:47",
      "imageUrl": ""
    },
    {
      "recommendScore": "59",
      "recommendCount": "94",
      "title": "[閒聊] 小迪算是低調紅的啦啦隊嗎",
      "link": "/bbs/BaseballXXXX/M.1769506340.A.022",
      "author": "adamcha",
      "board": "BaseballXXXX",
      "publishTime": "2026/01/27 09:32",
      "imageUrl": ""
    },
    {
      "recommendScore": "22",
      "recommendCount": "96",
      "title": "[新聞] 1.25兆特別條例遭白營砍剩4000億 國防部：版本窒礙難行",
      "link": "/bbs/Gossiping/M.1769483219.A.EC0",
      "author": "mongi",
      "board": "Gossiping",
      "publishTime": "2026/01/27 03:06",
      "imageUrl": ""
    },
    {
      "recommendScore": "68",
      "recommendCount": "172",
      "title": "[閒聊] 國旅",
      "link": "/bbs/BaseballXXXX/M.1769477128.A.95A",
      "author": "PaiChiou",
      "board": "BaseballXXXX",
      "publishTime": "2026/01/27 01:25",
      "imageUrl": ""
    },
    {
      "recommendScore": "26",
      "recommendCount": "78",
      "title": "[問卦] 連女醫師都在當網紅賣肉？",
      "link": "/bbs/Gossiping/M.1769481269.A.ABC",
      "author": "attpp",
      "board": "Gossiping",
      "publishTime": "2026/01/27 02:34",
      "imageUrl": ""
    },
    {
      "recommendScore": "39",
      "recommendCount": "56",
      "title": "[閒聊] 賈永婕的比喻恰當嗎？",
      "link": "/bbs/BaseballXXXX/M.1769488429.A.956",
      "author": "TsukimiyaAyu",
      "board": "BaseballXXXX",
      "publishTime": "2026/01/27 04:33",
      "imageUrl": ""
    },
    {
      "recommendScore": "26",
      "recommendCount": "79",
      "title": "[問卦] 美大使：加拿大不買F35 美戰機將進入領空",
      "link": "/bbs/Gossiping/M.1769480279.A.C31",
      "author": "bluehttp",
      "board": "Gossiping",
      "publishTime": "2026/01/27 02:17",
      "imageUrl": "https://cache.pttweb.cc/imgur/tpU6zoX/s/517bc0030605ca6ba1d4b74d358a9b33"
    },
    {
      "recommendScore": "8",
      "recommendCount": "54",
      "title": "[新聞] 財報出爐！去年大賺729億元 台電：盈餘將",
      "link": "/bbs/Gossiping/M.1769510040.A.270",
      "author": "Virness",
      "board": "Gossiping",
      "publishTime": "2026/01/27 10:34",
      "imageUrl": ""
    },
    {
      "recommendScore": "27",
      "recommendCount": "83",
      "title": "[閒聊] 會怕澳洲捷克的",
      "link": "/bbs/BaseballXXXX/M.1769509485.A.9C7",
      "author": "Kaoru93",
      "board": "BaseballXXXX",
      "publishTime": "2026/01/27 10:24",
      "imageUrl": ""
    },
    {
      "recommendScore": "19",
      "recommendCount": "65",
      "title": "[討論] 黃國昌：我們不會審民眾黨版的軍購條例",
      "link": "/bbs/HatePolitics/M.1769516773.A.40C",
      "author": "Whitening",
      "board": "HatePolitics",
      "publishTime": "2026/01/27 12:26",
      "imageUrl": ""
    },
    {
      "recommendScore": "46",
      "recommendCount": "142",
      "title": "[討論] 小南的年收入>三李嗎？",
      "link": "/bbs/BaseballXXXX/M.1769513614.A.107",
      "author": "qaz811223",
      "board": "BaseballXXXX",
      "publishTime": "2026/01/27 11:33",
      "imageUrl": ""
    },
    {
      "recommendScore": "39",
      "recommendCount": "39",
      "title": "[發錢] 迪亞哥FGO 第二部 開幕 DC群組推廣",
      "link": "/bbs/C_Chat/M.1769483245.A.21E",
      "author": "boss0322",
      "board": "C_Chat",
      "publishTime": "2026/01/27 03:07",
      "imageUrl": ""
    },
    {
      "recommendScore": "-3",
      "recommendCount": "42",
      "title": "[新聞] 小心出國「被送中」！外交部旅遊警示",
      "link": "/bbs/Gossiping/M.1769516179.A.DAC",
      "author": "alex1987",
      "board": "Gossiping",
      "publishTime": "2026/01/27 12:16",
      "imageUrl": ""
    },
    {
      "recommendScore": "23",
      "recommendCount": "41",
      "title": "[問卦] 新台幣面額三千紙鈔要放誰？",
      "link": "/bbs/Gossiping/M.1769487088.A.D60",
      "author": "popo1234",
      "board": "Gossiping",
      "publishTime": "2026/01/27 04:11",
      "imageUrl": ""
    },
    {
      "recommendScore": "-8",
      "recommendCount": "59",
      "title": "[新聞] 賴總統：審預算是國會責任 不是要求總統府配合的籌碼",
      "link": "/bbs/Gossiping/M.1769523752.A.FE4",
      "author": "ccf52881",
      "board": "Gossiping",
      "publishTime": "2026/01/27 14:22",
      "imageUrl": ""
    },
    {
      "recommendScore": "23",
      "recommendCount": "72",
      "title": "[新聞] 川普突漲韓關稅 25% 嚇壞台商！許舒博引韓為戒：台美關稅協議若卡關",
      "link": "/bbs/HatePolitics/M.1769480898.A.8BC",
      "author": "boogieman",
      "board": "HatePolitics",
      "publishTime": "2026/01/27 02:28",
      "imageUrl": ""
    },
    {
      "recommendScore": "24",
      "recommendCount": "41",
      "title": "[新聞] 高雄住商大樓水龍頭冒出「紅線蟲」 多人上吐下瀉還有住戶險喪命",
      "link": "/bbs/Gossiping/M.1769523789.A.AA1",
      "author": "armorblocks",
      "board": "Gossiping",
      "publishTime": "2026/01/27 14:23",
      "imageUrl": "https://cache.pttweb.cc/imgur/PeKzPS4/s/2b3b605709e10590602a4dffeda4196c"
    },
    {
      "recommendScore": "-5",
      "recommendCount": "47",
      "title": "[新聞] 關鍵在今午！10度封殺軍購北京就點頭 國民黨明宣布赴中「準智庫交流」",
      "link": "/bbs/Gossiping/M.1769486487.A.55A",
      "author": "drea",
      "board": "Gossiping",
      "publishTime": "2026/01/27 04:01",
      "imageUrl": ""
    }
  ]
}