{
  "updated": "2026-01-09T16:50:09.772Z",
  "total_found": 20,
  "returned_count": 20,
  "articles": [
    {
      "recommendScore": "193",
      "recommendCount": "236",
      "title": "[爆卦] 地震",
      "link": "/bbs/Gossiping/M.1767889857.A.F9B",
      "author": "dodoro1",
      "board": "Gossiping",
      "publishTime": "2026/01/08 16:30",
      "imageUrl": ""
    },
    {
      "recommendScore": "94",
      "recommendCount": "522",
      "title": "[討論] 營養午餐有必要免費嗎",
      "link": "/bbs/HatePolitics/M.1767950224.A.BB2",
      "author": "foam0406",
      "board": "HatePolitics",
      "publishTime": "2026/01/09 09:17",
      "imageUrl": ""
    },
    {
      "recommendScore": "646",
      "recommendCount": "1049",
      "title": "[電競] 2026 LCK Season Opening",
      "link": "/bbs/LoL/M.1767947671.A.B98",
      "author": "laptic",
      "board": "LoL",
      "publishTime": "2026/01/09 08:34",
      "imageUrl": "https://cache.pttweb.cc/imgur/gnIUjXP/s/59a67147c8e9f163df79729c91c55a03"
    },
    {
      "recommendScore": "75",
      "recommendCount": "345",
      "title": "Re: [新聞] 陳昭姿回擊林國成：誰考試不及格？　我跟柯文哲定的不是兩年條款",
      "link": "/bbs/Gossiping/M.1767941138.A.6F1",
      "author": "BlueBird5566",
      "board": "Gossiping",
      "publishTime": "2026/01/09 06:45",
      "imageUrl": ""
    },
    {
      "recommendScore": "254",
      "recommendCount": "453",
      "title": "[討論] [Vtub] Hololive 晚間直播單 (1150108)",
      "link": "/bbs/C_Chat/M.1767869385.A.84C",
      "author": "laptic",
      "board": "C_Chat",
      "publishTime": "2026/01/08 10:49",
      "imageUrl": ""
    },
    {
      "recommendScore": "-43",
      "recommendCount": "146",
      "title": "Re: [情報] 台積公司2025年12月營收報告 y+20.4% m-2.5%",
      "link": "/bbs/Stock/M.1767942094.A.656",
      "author": "icrose",
      "board": "Stock",
      "publishTime": "2026/01/09 07:01",
      "imageUrl": ""
    },
    {
      "recommendScore": "104",
      "recommendCount": "110",
      "title": "[發錢] 異國日記 第一集 堪稱我看過最好的改編",
      "link": "/bbs/C_Chat/M.1767895433.A.BAF",
      "author": "jeeplong",
      "board": "C_Chat",
      "publishTime": "2026/01/08 18:03",
      "imageUrl": ""
    },
    {
      "recommendScore": "74",
      "recommendCount": "128",
      "title": "[情報] 0109 上市外資買賣超排行",
      "link": "/bbs/Stock/M.1767946247.A.081",
      "author": "saber50116",
      "board": "Stock",
      "publishTime": "2026/01/09 08:10",
      "imageUrl": ""
    },
    {
      "recommendScore": "70",
      "recommendCount": "141",
      "title": "[新聞] 黃偉哲宣布 台南營養午餐全面免費",
      "link": "/bbs/Tainan/M.1767946349.A.8A8",
      "author": "Zero0910",
      "board": "Tainan",
      "publishTime": "2026/01/09 08:12",
      "imageUrl": ""
    },
    {
      "recommendScore": "78",
      "recommendCount": "195",
      "title": "[閒聊] 借200萬輸70萬了怎麼辦?",
      "link": "/bbs/SportLottery/M.1767952109.A.C07",
      "author": "tazac",
      "board": "SportLottery",
      "publishTime": "2026/01/09 09:48",
      "imageUrl": ""
    },
    {
      "recommendScore": "71",
      "recommendCount": "150",
      "title": "[新聞] 快訊》跟進其他縣市 黃偉哲宣布：台南營養午餐9月起全面免費",
      "link": "/bbs/HatePolitics/M.1767946196.A.2D1",
      "author": "CrazySept",
      "board": "HatePolitics",
      "publishTime": "2026/01/09 08:09",
      "imageUrl": ""
    },
    {
      "recommendScore": "79",
      "recommendCount": "111",
      "title": "[問卦] 請幫取狗名",
      "link": "/bbs/Gossiping/M.1767891836.A.E98",
      "author": "KittyColnago",
      "board": "Gossiping",
      "publishTime": "2026/01/08 17:03",
      "imageUrl": ""
    },
    {
      "recommendScore": "75",
      "recommendCount": "175",
      "title": "[閒聊] 全境封鎖3製作中 會是大的 不能說太多",
      "link": "/bbs/C_Chat/M.1767940897.A.A7B",
      "author": "w790818",
      "board": "C_Chat",
      "publishTime": "2026/01/09 06:41",
      "imageUrl": ""
    },
    {
      "recommendScore": "68",
      "recommendCount": "112",
      "title": "[情報] 115年01月09日 三大法人買賣金額統計表",
      "link": "/bbs/Stock/M.1767942147.A.368",
      "author": "coconing",
      "board": "Stock",
      "publishTime": "2026/01/09 07:02",
      "imageUrl": ""
    },
    {
      "recommendScore": "53",
      "recommendCount": "166",
      "title": "[新聞] 林妍霏槓上李多慧！味全龍89字反擊：幽默不該建立在貶低他人之上",
      "link": "/bbs/Baseball/M.1767947095.A.EE5",
      "author": "westdoorcard",
      "board": "Baseball",
      "publishTime": "2026/01/09 08:24",
      "imageUrl": ""
    },
    {
      "recommendScore": "75",
      "recommendCount": "150",
      "title": "[情報] 2344華邦電 11月自結 EPS 0.21",
      "link": "/bbs/Stock/M.1767943745.A.2A3",
      "author": "sayforever69",
      "board": "Stock",
      "publishTime": "2026/01/09 07:29",
      "imageUrl": ""
    },
    {
      "recommendScore": "139",
      "recommendCount": "245",
      "title": "[LIVE] 澳甲足球-奧克蘭@布里斯本 2:0 場中",
      "link": "/bbs/SportLottery/M.1767946569.A.F05",
      "author": "laylun",
      "board": "SportLottery",
      "publishTime": "2026/01/09 08:16",
      "imageUrl": ""
    },
    {
      "recommendScore": "67",
      "recommendCount": "117",
      "title": "[花邊] JDub:三年來雷霆贏太多,輸幾場就大驚小怪",
      "link": "/bbs/NBA/M.1767947364.A.2C5",
      "author": "Tonyx599026",
      "board": "NBA",
      "publishTime": "2026/01/09 08:29",
      "imageUrl": "https://cache.pttweb.cc/imgur/g8ODIJq/s/ef56f68302d6c26d7897dec75fc628dc"
    },
    {
      "recommendScore": "49",
      "recommendCount": "116",
      "title": "[情報] 台積公司2025年12月營收報告 y+20.4% m-2.5%",
      "link": "/bbs/Stock/M.1767936707.A.336",
      "author": "MOMO0478",
      "board": "Stock",
      "publishTime": "2026/01/09 05:31",
      "imageUrl": ""
    },
    {
      "recommendScore": "70",
      "recommendCount": "110",
      "title": "[情報] AD左手受傷",
      "link": "/bbs/NBA/M.1767932139.A.9D7",
      "author": "dragon803",
      "board": "NBA",
      "publishTime": "2026/01/09 04:15",
      "imageUrl": ""
    }
  ]
}