{
  "updated": "2025-08-12T16:06:52.186Z",
  "total_found": 20,
  "returned_count": 20,
  "articles": [
    {
      "recommendScore": "995",
      "recommendCount": "1424",
      "title": "[爆卦] 林俊言疑似變造公文",
      "link": "/bbs/Gossiping/M.1755000842.A.6B5",
      "author": "BaoLiao5566",
      "board": "Gossiping",
      "publishTime": "2025/08/12 12:14",
      "imageUrl": "https://cache.pttweb.cc/imgur/KdaCt2k/s/0a1567671a2978bd1730027f64ae6da7"
    },
    {
      "recommendScore": "704",
      "recommendCount": "1088",
      "title": "[新聞] 廁所有人男好心提醒 女大生竟嗆干你屁事",
      "link": "/bbs/Gossiping/M.1754968831.A.991",
      "author": "cl3bp6",
      "board": "Gossiping",
      "publishTime": "2025/08/12 03:20",
      "imageUrl": ""
    },
    {
      "recommendScore": "619",
      "recommendCount": "1427",
      "title": "[問卦] 一起來幫反核少女想學經歷好嗎",
      "link": "/bbs/Gossiping/M.1754958987.A.797",
      "author": "rz2x",
      "board": "Gossiping",
      "publishTime": "2025/08/12 00:36",
      "imageUrl": ""
    },
    {
      "recommendScore": "405",
      "recommendCount": "1011",
      "title": "[新聞] 南韓官員怒轟台灣「外交失禮」登上韓媒：留下傲慢的印象",
      "link": "/bbs/Gossiping/M.1754949695.A.5F8",
      "author": "yahe0526",
      "board": "Gossiping",
      "publishTime": "2025/08/11 22:01",
      "imageUrl": ""
    },
    {
      "recommendScore": "342",
      "recommendCount": "828",
      "title": "[問卦] 脆熱議：726後你們後悔了吧",
      "link": "/bbs/Gossiping/M.1754954963.A.3B2",
      "author": "lonzoball02",
      "board": "Gossiping",
      "publishTime": "2025/08/11 23:29",
      "imageUrl": "https://cache.pttweb.cc/imgur/NPLhX7e/s/e37bee68131d5963b3e872722d6a0683"
    },
    {
      "recommendScore": "341",
      "recommendCount": "814",
      "title": "[新聞] 要以死控訴司法 陳佩琪突拋明法院跳樓：也請在我面前槍斃柯文哲",
      "link": "/bbs/Gossiping/M.1754995935.A.866",
      "author": "ihl123456",
      "board": "Gossiping",
      "publishTime": "2025/08/12 10:52",
      "imageUrl": ""
    },
    {
      "recommendScore": "538",
      "recommendCount": "822",
      "title": "Re: [爆卦] 林俊言疑似變造公文",
      "link": "/bbs/Gossiping/M.1755008241.A.1EE",
      "author": "Dayton",
      "board": "Gossiping",
      "publishTime": "2025/08/12 14:17",
      "imageUrl": ""
    },
    {
      "recommendScore": "368",
      "recommendCount": "1346",
      "title": "Re: [問卦] 黃士修一直罵反核無腦 你難道不生氣嗎",
      "link": "/bbs/Gossiping/M.1754933932.A.4B3",
      "author": "TCPai",
      "board": "Gossiping",
      "publishTime": "2025/08/11 17:38",
      "imageUrl": ""
    },
    {
      "recommendScore": "448",
      "recommendCount": "592",
      "title": "[情報] 邦魯閣",
      "link": "/bbs/Baseball/M.1754996606.A.28D",
      "author": "HardDDDD",
      "board": "Baseball",
      "publishTime": "2025/08/12 11:03",
      "imageUrl": ""
    },
    {
      "recommendScore": "291",
      "recommendCount": "594",
      "title": "[問卦] 南部老人現在一直在罵…？",
      "link": "/bbs/Gossiping/M.1754980177.A.4E9",
      "author": "aa1477888",
      "board": "Gossiping",
      "publishTime": "2025/08/12 06:29",
      "imageUrl": ""
    },
    {
      "recommendScore": "295",
      "recommendCount": "671",
      "title": "[新聞] 綠營慘敗檢討竟喊「民進黨是媒體弱勢」",
      "link": "/bbs/Gossiping/M.1754992720.A.69C",
      "author": "ntupeap",
      "board": "Gossiping",
      "publishTime": "2025/08/12 09:58",
      "imageUrl": ""
    },
    {
      "recommendScore": "321",
      "recommendCount": "532",
      "title": "[問卦] 反核少女學經歷可以去哪上班 ?",
      "link": "/bbs/Gossiping/M.1754964930.A.B6B",
      "author": "dnzteeqrq",
      "board": "Gossiping",
      "publishTime": "2025/08/12 02:15",
      "imageUrl": ""
    },
    {
      "recommendScore": "198",
      "recommendCount": "539",
      "title": "[新聞] 中颱楊柳進逼！3萬餘國軍待命　國防部：救災視同作戰",
      "link": "/bbs/Gossiping/M.1755004934.A.9CB",
      "author": "chopper594",
      "board": "Gossiping",
      "publishTime": "2025/08/12 13:22",
      "imageUrl": ""
    },
    {
      "recommendScore": "147",
      "recommendCount": "607",
      "title": "[新聞] 檢察官回：隨身碟數字即賄款",
      "link": "/bbs/Gossiping/M.1754998128.A.3B4",
      "author": "ndhuctc",
      "board": "Gossiping",
      "publishTime": "2025/08/12 11:28",
      "imageUrl": ""
    },
    {
      "recommendScore": "264",
      "recommendCount": "526",
      "title": "[新聞] 颱風路徑南修 南部居民嘆「已舀水舀到怕」：心好累",
      "link": "/bbs/Gossiping/M.1754973037.A.9D5",
      "author": "schwalbe",
      "board": "Gossiping",
      "publishTime": "2025/08/12 04:30",
      "imageUrl": ""
    },
    {
      "recommendScore": "294",
      "recommendCount": "666",
      "title": "[新聞] 賴清德慘了！美媒分析「共和黨疏遠台灣」：兩大原因造成不願冒險",
      "link": "/bbs/Gossiping/M.1754973855.A.0D5",
      "author": "jordanlove",
      "board": "Gossiping",
      "publishTime": "2025/08/12 04:44",
      "imageUrl": ""
    },
    {
      "recommendScore": "275",
      "recommendCount": "620",
      "title": "[新聞] 學者指賴清德失去讀賣、產經支持 小笠原：還有朝日新聞",
      "link": "/bbs/Gossiping/M.1754962497.A.85B",
      "author": "SAgirl",
      "board": "Gossiping",
      "publishTime": "2025/08/12 01:34",
      "imageUrl": ""
    },
    {
      "recommendScore": "-236",
      "recommendCount": "493",
      "title": "[新聞] 世界僅台灣做到！揭關稅公開透明4作為",
      "link": "/bbs/Gossiping/M.1754975145.A.1A9",
      "author": "koei5566",
      "board": "Gossiping",
      "publishTime": "2025/08/12 05:05",
      "imageUrl": ""
    },
    {
      "recommendScore": "271",
      "recommendCount": "565",
      "title": "[新聞] 柯文哲案「洩密源」找到了？ 裴偉「偵查中」訪邱佩琳問Excel檔",
      "link": "/bbs/Gossiping/M.1754981075.A.215",
      "author": "cheninher",
      "board": "Gossiping",
      "publishTime": "2025/08/12 06:44",
      "imageUrl": ""
    },
    {
      "recommendScore": "265",
      "recommendCount": "428",
      "title": "[問卦] 為何颱風和鋒面都精準的跑去高雄台南？",
      "link": "/bbs/Gossiping/M.1754960415.A.EB7",
      "author": "TFBoys",
      "board": "Gossiping",
      "publishTime": "2025/08/12 01:00",
      "imageUrl": ""
    }
  ]
}