{
  "updated": "2026-02-03T11:52:18.411Z",
  "total_found": 20,
  "returned_count": 20,
  "articles": [
    {
      "recommendScore": "137",
      "recommendCount": "158",
      "title": "Re: [LIVE] 新超 芽籠國際 @ 新加坡新潟天鵝 場中",
      "link": "/bbs/SportLottery/M.1770038572.A.186",
      "author": "lotterywin",
      "board": "SportLottery",
      "publishTime": "2026/02/02 13:22",
      "imageUrl": ""
    },
    {
      "recommendScore": "95",
      "recommendCount": "146",
      "title": "[情報] 2408 南亞科115年1月營收",
      "link": "/bbs/Stock/M.1770102162.A.FF4",
      "author": "BlueBird5566",
      "board": "Stock",
      "publishTime": "2026/02/03 07:02",
      "imageUrl": ""
    },
    {
      "recommendScore": "72",
      "recommendCount": "137",
      "title": "[新聞] 日本訂車爽約還封鎖起底竟是高雄人！業者嘆：信譽很重要",
      "link": "/bbs/Gossiping/M.1770036267.A.D5A",
      "author": "ihl123456",
      "board": "Gossiping",
      "publishTime": "2026/02/02 12:44",
      "imageUrl": ""
    },
    {
      "recommendScore": "87",
      "recommendCount": "131",
      "title": "[新聞] 黃仁勳談輝達總部簽約進度直言市長幫了很大的忙",
      "link": "/bbs/Gossiping/M.1770046607.A.E17",
      "author": "tsengcc",
      "board": "Gossiping",
      "publishTime": "2026/02/02 15:36",
      "imageUrl": ""
    },
    {
      "recommendScore": "84",
      "recommendCount": "163",
      "title": "[外絮] 乳摸:鬍子跟Garland互換討論已達後期階段",
      "link": "/bbs/NBA/M.1770092394.A.B03",
      "author": "pneumo",
      "board": "NBA",
      "publishTime": "2026/02/03 04:19",
      "imageUrl": ""
    },
    {
      "recommendScore": "45",
      "recommendCount": "93",
      "title": "[新聞] 輝達「南台灣設總部」？黃仁勳:多數工程師都在台北",
      "link": "/bbs/Stock/M.1770044615.A.381",
      "author": "zkow",
      "board": "Stock",
      "publishTime": "2026/02/02 15:03",
      "imageUrl": ""
    },
    {
      "recommendScore": "65",
      "recommendCount": "108",
      "title": "[標的] 該怎麼做正2價差?",
      "link": "/bbs/Stock/M.1770046843.A.FB6",
      "author": "rz2x",
      "board": "Stock",
      "publishTime": "2026/02/02 15:40",
      "imageUrl": ""
    },
    {
      "recommendScore": "59",
      "recommendCount": "93",
      "title": "[花邊] 狄龍:我聽說字母哥是去勇士隊",
      "link": "/bbs/NBA/M.1770037866.A.710",
      "author": "kakala99",
      "board": "NBA",
      "publishTime": "2026/02/02 13:11",
      "imageUrl": ""
    },
    {
      "recommendScore": "44",
      "recommendCount": "84",
      "title": "[新聞] 台股三天蒸發逾千點 金管會信心喊話！",
      "link": "/bbs/Stock/M.1770036183.A.8BA",
      "author": "xephon",
      "board": "Stock",
      "publishTime": "2026/02/02 12:43",
      "imageUrl": ""
    },
    {
      "recommendScore": "62",
      "recommendCount": "91",
      "title": "[閒聊] 張肇元",
      "link": "/bbs/BaseballXXXX/M.1770106667.A.97C",
      "author": "kensukeshu",
      "board": "BaseballXXXX",
      "publishTime": "2026/02/03 08:17",
      "imageUrl": ""
    },
    {
      "recommendScore": "17",
      "recommendCount": "120",
      "title": "[新聞]「民進黨非常重視兩岸！」　賴清德示警藍營做這1事：對台灣危險",
      "link": "/bbs/Gossiping/M.1770092173.A.48A",
      "author": "guido",
      "board": "Gossiping",
      "publishTime": "2026/02/03 04:16",
      "imageUrl": ""
    },
    {
      "recommendScore": "53",
      "recommendCount": "76",
      "title": "[分享] 「匹敵莫伊內羅」最速158公里 徐若熙的「",
      "link": "/bbs/Baseball/M.1770042871.A.12F",
      "author": "newsbow",
      "board": "Baseball",
      "publishTime": "2026/02/02 14:34",
      "imageUrl": ""
    },
    {
      "recommendScore": "42",
      "recommendCount": "112",
      "title": "[討論] 廠商聽玩家的意見修改是不自信的表現嗎？",
      "link": "/bbs/C_Chat/M.1770036307.A.C26",
      "author": "kl50365",
      "board": "C_Chat",
      "publishTime": "2026/02/02 12:45",
      "imageUrl": "https://cache.pttweb.cc/imgur/xiXfT5N/s/143a995715c21ce5dc39530ed214603b"
    },
    {
      "recommendScore": "60",
      "recommendCount": "65",
      "title": "[瓦特] 六萬訂閱",
      "link": "/bbs/Marginalman/M.1770047406.A.028",
      "author": "HGK",
      "board": "Marginalman",
      "publishTime": "2026/02/02 15:50",
      "imageUrl": ""
    },
    {
      "recommendScore": "57",
      "recommendCount": "81",
      "title": "[新聞] 多名球星不能打經典賽！波多黎各開嗆：美國乾脆自己找日本玩",
      "link": "/bbs/Baseball/M.1770033639.A.64A",
      "author": "jganet",
      "board": "Baseball",
      "publishTime": "2026/02/02 12:00",
      "imageUrl": ""
    },
    {
      "recommendScore": "36",
      "recommendCount": "71",
      "title": "[標的] 華邦電籌碼分析",
      "link": "/bbs/Stock/M.1770036689.A.DE1",
      "author": "minazukimaya",
      "board": "Stock",
      "publishTime": "2026/02/02 12:51",
      "imageUrl": ""
    },
    {
      "recommendScore": "43",
      "recommendCount": "76",
      "title": "[新聞] 葛萊美／女星上空走紅毯！「兩點全露」只靠乳環撐住薄紗",
      "link": "/bbs/Gossiping/M.1770034913.A.E7F",
      "author": "proprome",
      "board": "Gossiping",
      "publishTime": "2026/02/02 12:21",
      "imageUrl": ""
    },
    {
      "recommendScore": "50",
      "recommendCount": "67",
      "title": "[情報] 115年02月02日信用交易統計",
      "link": "/bbs/Stock/M.1770038476.A.344",
      "author": "steward135",
      "board": "Stock",
      "publishTime": "2026/02/02 13:21",
      "imageUrl": ""
    },
    {
      "recommendScore": "55",
      "recommendCount": "70",
      "title": "[閒聊] 大暮維人 人在法國 收到電動直排輪",
      "link": "/bbs/C_Chat/M.1770044075.A.B5F",
      "author": "w790818",
      "board": "C_Chat",
      "publishTime": "2026/02/02 14:54",
      "imageUrl": ""
    },
    {
      "recommendScore": "47",
      "recommendCount": "124",
      "title": "[情報] 近年MVP在一體化數據LEBRON的排名",
      "link": "/bbs/NBA/M.1770043004.A.86C",
      "author": "jeff1013",
      "board": "NBA",
      "publishTime": "2026/02/02 14:36",
      "imageUrl": ""
    }
  ]
}