{
  "updated": "2026-05-30T08:09:19.096Z",
  "total_found": 20,
  "returned_count": 20,
  "articles": [
    {
      "recommendScore": "438",
      "recommendCount": "1181",
      "title": "[新聞] 核四啟用發電 綠民調近8成支持",
      "link": "/bbs/Gossiping/M.1780105890.A.24F",
      "author": "ptt987654321",
      "board": "Gossiping",
      "publishTime": "2026/05/30 01:51",
      "imageUrl": ""
    },
    {
      "recommendScore": "438",
      "recommendCount": "465",
      "title": "[情報] Guardians Select Stuart Fairchild",
      "link": "/bbs/Baseball/M.1780081816.A.6E6",
      "author": "sam9595",
      "board": "Baseball",
      "publishTime": "2026/05/29 19:10",
      "imageUrl": ""
    },
    {
      "recommendScore": "383",
      "recommendCount": "603",
      "title": "[分享] 林書逸:我以為兄弟加油聲很大聲",
      "link": "/bbs/Baseball/M.1780064170.A.F96",
      "author": "micheal59",
      "board": "Baseball",
      "publishTime": "2026/05/29 14:16",
      "imageUrl": ""
    },
    {
      "recommendScore": "240",
      "recommendCount": "482",
      "title": "[請益] 股市大漲，何時獲利了結？",
      "link": "/bbs/Stock/M.1780049048.A.FCC",
      "author": "foxher",
      "board": "Stock",
      "publishTime": "2026/05/29 10:04",
      "imageUrl": ""
    },
    {
      "recommendScore": "295",
      "recommendCount": "384",
      "title": "[情報] 115年05月29日信用交易統計",
      "link": "/bbs/Stock/M.1780061493.A.3D5",
      "author": "steward135",
      "board": "Stock",
      "publishTime": "2026/05/29 13:31",
      "imageUrl": ""
    },
    {
      "recommendScore": "270",
      "recommendCount": "424",
      "title": "[新聞] 「放鳥美智庫」大反轉！主席親向鄭麗文致歉：綠營消息人士太愚蠢",
      "link": "/bbs/Gossiping/M.1780060999.A.450",
      "author": "CREA",
      "board": "Gossiping",
      "publishTime": "2026/05/29 13:23",
      "imageUrl": ""
    },
    {
      "recommendScore": "72",
      "recommendCount": "368",
      "title": "[新聞] 黃仁勳4度說要有「電力」 沈伯洋：印證我們講的要有變電所",
      "link": "/bbs/Gossiping/M.1780052280.A.C10",
      "author": "tsaotsaogh",
      "board": "Gossiping",
      "publishTime": "2026/05/29 10:58",
      "imageUrl": ""
    },
    {
      "recommendScore": "231",
      "recommendCount": "347",
      "title": "[問卦] 股票漲爆，有什麼金錢觀扭曲的行為嗎",
      "link": "/bbs/Gossiping/M.1780045912.A.07E",
      "author": "WRXSTi",
      "board": "Gossiping",
      "publishTime": "2026/05/29 09:11",
      "imageUrl": ""
    },
    {
      "recommendScore": "289",
      "recommendCount": "426",
      "title": "[分享] 今日鄧愷威 5局7K 3ER",
      "link": "/bbs/Baseball/M.1780110341.A.FAC",
      "author": "Eric102990",
      "board": "Baseball",
      "publishTime": "2026/05/30 03:05",
      "imageUrl": ""
    },
    {
      "recommendScore": "170",
      "recommendCount": "402",
      "title": "[問卦] Threads開始在黑黃仁勳了？？",
      "link": "/bbs/Gossiping/M.1780043758.A.FC3",
      "author": "Vanced",
      "board": "Gossiping",
      "publishTime": "2026/05/29 08:35",
      "imageUrl": ""
    },
    {
      "recommendScore": "-75",
      "recommendCount": "325",
      "title": "[討論] SGA今年奪冠的話是不是就超越Kobe了？",
      "link": "/bbs/NBA/M.1780109047.A.9C2",
      "author": "sth336",
      "board": "NBA",
      "publishTime": "2026/05/30 02:44",
      "imageUrl": ""
    },
    {
      "recommendScore": "206",
      "recommendCount": "280",
      "title": "[分享]今日林書逸",
      "link": "/bbs/Baseball/M.1780061064.A.C35",
      "author": "suwagutao",
      "board": "Baseball",
      "publishTime": "2026/05/29 13:24",
      "imageUrl": ""
    },
    {
      "recommendScore": "231",
      "recommendCount": "316",
      "title": "[新聞]和周星馳對罵成經典!《九品芝麻官》李公公劉洵驚傳離世",
      "link": "/bbs/Gossiping/M.1780105566.A.309",
      "author": "linhu8883324",
      "board": "Gossiping",
      "publishTime": "2026/05/30 01:46",
      "imageUrl": ""
    },
    {
      "recommendScore": "115",
      "recommendCount": "326",
      "title": "[新聞] 快新聞／台北市竟傳「藍綠已翻盤」！他看民調驚吐1現象：民進黨選舉大有可為",
      "link": "/bbs/Gossiping/M.1780056218.A.FFD",
      "author": "iam168888888",
      "board": "Gossiping",
      "publishTime": "2026/05/29 12:03",
      "imageUrl": ""
    },
    {
      "recommendScore": "241",
      "recommendCount": "500",
      "title": "[新聞] 淡水緊張了？議員率眾進議會爭大巨蛋落腳樹林 選址結果「7月會公布」",
      "link": "/bbs/Baseball/M.1780043347.A.C6F",
      "author": "JAL96",
      "board": "Baseball",
      "publishTime": "2026/05/29 08:29",
      "imageUrl": ""
    },
    {
      "recommendScore": "257",
      "recommendCount": "361",
      "title": "[新聞] KAT愛尼克　從林來瘋開始",
      "link": "/bbs/NBA/M.1780099498.A.DF1",
      "author": "thnlkj0665",
      "board": "NBA",
      "publishTime": "2026/05/30 00:04",
      "imageUrl": ""
    },
    {
      "recommendScore": "199",
      "recommendCount": "269",
      "title": "[新聞] 藍白光誤事 洪總：我們也有經驗",
      "link": "/bbs/Baseball/M.1780065360.A.BE6",
      "author": "ruka660101",
      "board": "Baseball",
      "publishTime": "2026/05/29 14:36",
      "imageUrl": ""
    },
    {
      "recommendScore": "88",
      "recommendCount": "338",
      "title": "[新聞] 高雄教師墜樓身亡 教育部發聲了",
      "link": "/bbs/Gossiping/M.1780051201.A.C1A",
      "author": "EstelleRinz",
      "board": "Gossiping",
      "publishTime": "2026/05/29 10:40",
      "imageUrl": ""
    },
    {
      "recommendScore": "158",
      "recommendCount": "294",
      "title": "[問卦] 國軍下令：不要再稱新兵為「小朋友」！",
      "link": "/bbs/Gossiping/M.1780054058.A.0FC",
      "author": "pigpigcom123",
      "board": "Gossiping",
      "publishTime": "2026/05/29 11:27",
      "imageUrl": ""
    },
    {
      "recommendScore": "190",
      "recommendCount": "318",
      "title": "[分享] CPBL戰績",
      "link": "/bbs/Baseball/M.1780062541.A.932",
      "author": "nybbnan",
      "board": "Baseball",
      "publishTime": "2026/05/29 13:49",
      "imageUrl": ""
    }
  ]
}